mycluster/__init__.py
mycluster/cli.py
mycluster/exceptions.py
mycluster/schedulers/__init__.py
mycluster/schedulers/base.py
mycluster/schedulers/lsf.py
mycluster/schedulers/pbs.py
mycluster/schedulers/sge.py
mycluster/schedulers/slurm.py
mycluster/schedulers/templates/lsf.jinja
mycluster/schedulers/templates/pbs.jinja
mycluster/schedulers/templates/sge.jinja
mycluster/schedulers/templates/slurm.jinja
mycluster-2.0.6.data/data/share/MyCluster/mycluster-OF-simpleFoam.bsh
mycluster-2.0.6.data/data/share/MyCluster/mycluster-fluent.bsh
mycluster-2.0.6.data/data/share/MyCluster/mycluster-paraview.bsh
mycluster-2.0.6.data/data/share/MyCluster/mycluster-zcfd.bsh
mycluster-2.0.6.dist-info/LICENSE
mycluster-2.0.6.dist-info/METADATA
mycluster-2.0.6.dist-info/WHEEL
mycluster-2.0.6.dist-info/entry_points.txt
mycluster-2.0.6.dist-info/top_level.txt
mycluster-2.0.6.dist-info/RECORD
