Metadata-Version: 2.1
Name: mycluster
Version: 2.0.6
Summary: "Utilities to support interacting with multiple HPC clusters"
Home-page: https://github.com/zenotech/MyCluster
Author: "Zenotech Ltd"
Author-email: "support@zenotech.com"
License: BSD 3-Clause License
Classifier: License :: OSI Approved :: BSD License
Classifier: Programming Language :: Python :: 3
Classifier: Programming Language :: Python :: 3.6
Classifier: Programming Language :: Python :: 3.7
Classifier: Programming Language :: Python :: 3.8
License-File: LICENSE
Requires-Dist: Jinja2 (>=2.10.1)
Requires-Dist: click
Requires-Dist: pyfiglet
